dbtmeshification/__init__.py
dbtmeshification/__main__.py
dbtmeshification/cli.py
dbtmeshification/dbt/__init__.py
dbtmeshification/dbt/compile.py
dbtmeshification/dbt/parser.py
dbtmeshification/dbt/schemas.py
dbtmeshification/runner.py
dbtmeshification/specifications/__init__.py
dbtmeshification/specifications/parser.py
dbtmeshification/specifications/schemas.py
dbtmeshification/sqlglot/__init__.py
dbtmeshification/sqlglot/builder.py
dbtmeshification/sqlglot/parser.py
dbtmeshification/sqlglot/schemas.py
dbtmeshification-0.0.1.dist-info/WHEEL
dbtmeshification-0.0.1.dist-info/entry_points.txt
dbtmeshification-0.0.1.dist-info/METADATA
dbtmeshification-0.0.1.dist-info/RECORD
