Metadata-Version: 2.3
Name: dbtmeshification
Version: 0.0.1
Summary: A dbt companion for unit testing, column-level lineage, and more.
Keywords: dbt,testing,sqlmesh,data,analytics,sqlglot,duckdb
Author: Ahmed Muhammad
License: MIT
Classifier: Development Status :: 3 - Alpha
Classifier: Intended Audience :: Developers
Classifier: License :: OSI Approved :: MIT License
Classifier: Programming Language :: Python :: 3
Classifier: Programming Language :: Python :: 3.9
Classifier: Programming Language :: Python :: 3.10
Classifier: Programming Language :: Python :: 3.11
Classifier: Programming Language :: Python :: 3.12
Classifier: Programming Language :: Python :: 3.13
Classifier: Topic :: Software Development :: Testing
Classifier: Topic :: Database
Requires-Dist: sqlglot
Requires-Dist: dbt-core
Requires-Dist: duckdb
Requires-Dist: pyyaml
Requires-Dist: pytest ; extra == 'dev'
Requires-Python: >=3.9
Provides-Extra: dev
